setup.py
hilmituker/Binomialdistribution.py
hilmituker/Gaussiandistribution.py
hilmituker/Generaldistribution.py
hilmituker/__init__.py
hilmituker.egg-info/PKG-INFO
hilmituker.egg-info/SOURCES.txt
hilmituker.egg-info/dependency_links.txt
hilmituker.egg-info/not-zip-safe
hilmituker.egg-info/top_level.txt